{
  "CF159992816": {
    "contest_id": 588,
    "language": "GNU C++17",
    "path": "codeforces\\588\\A.cpp",
    "platform": "Codeforces",
    "problem_index": "A",
    "problem_name": "Duff and Meat",
    "problem_url": "https://codeforces.com/contest/588/problem/A",
    "submission_id": "CF159992816",
    "submission_url": "https://codeforces.com/contest/588/submission/159992816",
    "tags": [
      "greedy",
      "*900"
    ],
    "timestamp": "Jun/09/2022 12:43"
  },
  "CF160028170": {
    "contest_id": 588,
    "language": "GNU C++17",
    "path": "codeforces\\588\\B.cpp",
    "platform": "Codeforces",
    "problem_index": "B",
    "problem_name": "Duff in Love",
    "problem_url": "https://codeforces.com/contest/588/problem/B",
    "submission_id": "CF160028170",
    "submission_url": "https://codeforces.com/contest/588/submission/160028170",
    "tags": [
      "math",
      "*1300"
    ],
    "timestamp": "Jun/09/2022 20:48"
  },
  "CF160097789": {
    "contest_id": 1689,
    "language": "GNU C++17",
    "path": "codeforces\\1689\\A.cpp",
    "platform": "Codeforces",
    "problem_index": "A",
    "problem_name": "Lex String",
    "problem_url": "https://codeforces.com/contest/1689/problem/A",
    "submission_id": "CF160097789",
    "submission_url": "https://codeforces.com/contest/1689/submission/160097789",
    "tags": [
      "brute force",
      "greedy",
      "implementation",
      "sortings",
      "two pointers"
    ],
    "timestamp": "Jun/10/2022 22:51"
  },
  "CF160118480": {
    "contest_id": 1689,
    "language": "GNU C++17",
    "path": "codeforces\\1689\\B.cpp",
    "platform": "Codeforces",
    "problem_index": "B",
    "problem_name": "Mystic Permutation",
    "problem_url": "https://codeforces.com/contest/1689/problem/B",
    "submission_id": "CF160118480",
    "submission_url": "https://codeforces.com/contest/1689/submission/160118480",
    "tags": [
      "data structures",
      "greedy",
      "implementation"
    ],
    "timestamp": "Jun/10/2022 23:40"
  },
  "CF160170600": {
    "contest_id": 1057,
    "language": "GNU C++17",
    "path": "codeforces\\1057\\A.cpp",
    "platform": "Codeforces",
    "problem_index": "A",
    "problem_name": "Bmail Computer Network",
    "problem_url": "https://codeforces.com/contest/1057/problem/A",
    "submission_id": "CF160170600",
    "submission_url": "https://codeforces.com/contest/1057/submission/160170600",
    "tags": [
      "*special problem",
      "dfs and similar",
      "trees",
      "*900"
    ],
    "timestamp": "Jun/11/2022 12:59"
  }
}